_pwalk_core.pypy310-pp73-x86-linux-gnu.so
pwalk-0.1.6.dist-info/WHEEL
pwalk-0.1.6.dist-info/RECORD
pwalk-0.1.6.dist-info/top_level.txt
pwalk-0.1.6.dist-info/METADATA
pwalk-0.1.6.dist-info/entry_points.txt
pwalk-0.1.6.dist-info/licenses/LICENSE
pwalk/report.py
pwalk/__init__.py
pwalk/cli.py
pwalk/walk.py
pwalk/repair.py
