Metadata-Version: 2.4
Name: pwalk
Version: 0.1.6
Summary: High-performance parallel filesystem walker
Home-page: https://github.com/dirkpetersen/python-pwalk
Author: Dirk Petersen
Author-email: Dirk Petersen <dp@nowhere.com>
License: GPL-2.0
Project-URL: Homepage, https://github.com/dirkpetersen/python-pwalk
Project-URL: Repository, https://github.com/dirkpetersen/python-pwalk
Project-URL: Issues, https://github.com/dirkpetersen/python-pwalk/issues
Project-URL: Changelog, https://github.com/dirkpetersen/python-pwalk/releases
Keywords: filesystem,walk,parallel,performance,hpc,hpc-tools,storage-analysis
Classifier: Development Status :: 4 - Beta
Classifier: Intended Audience :: System Administrators
Classifier: Intended Audience :: Developers
Classifier: Topic :: System :: Filesystems
Classifier: Topic :: System :: Systems Administration
Classifier: License :: OSI Approved :: GNU General Public License v2 (GPLv2)
Classifier: Programming Language :: Python :: 3
Classifier: Programming Language :: Python :: 3.10
Classifier: Programming Language :: Python :: 3.11
Classifier: Programming Language :: Python :: 3.12
Classifier: Programming Language :: Python :: 3.13
Classifier: Programming Language :: Python :: 3.14
Classifier: Programming Language :: Python :: Implementation :: CPython
Classifier: Programming Language :: Python :: Implementation :: PyPy
Classifier: Programming Language :: C
Classifier: Operating System :: POSIX :: Linux
Requires-Python: >=3.10
License-File: LICENSE
Provides-Extra: dev
Requires-Dist: pytest>=7.0.0; extra == "dev"
Requires-Dist: pytest-cov>=4.0.0; extra == "dev"
Requires-Dist: pytest-benchmark>=4.0.0; extra == "dev"
Dynamic: author
Dynamic: home-page
Dynamic: license-file
Dynamic: requires-python
